launcha/__init__.py
launcha/launcha.py
launcha/template/main.tf
launcha/template/modules/cleanrl/main.tf
launcha/template/modules/cleanrl/setups.tf
launcha/template/modules/cleanrl/variables.tf
launcha-0.0.1.dist-info/entry_points.txt
launcha-0.0.1.dist-info/WHEEL
launcha-0.0.1.dist-info/METADATA
launcha-0.0.1.dist-info/RECORD
