Metadata-Version: 2.1
Name: launcha
Version: 0.0.1
Summary: 
Author: Costa Huang
Author-email: costa.huang@outlook.com
Requires-Python: >=3.7.1,<4.0.0
Classifier: Programming Language :: Python :: 3
Classifier: Programming Language :: Python :: 3.8
Classifier: Programming Language :: Python :: 3.9
Requires-Dist: boto3 (>=1.20.7,<2.0.0)
Requires-Dist: requests (>=2.26.0,<3.0.0)
Requires-Dist: wandb (>=0.12.6,<0.13.0)
